tstringlogger/__init__.py
tstringlogger-1.0.0.dist-info/METADATA
tstringlogger-1.0.0.dist-info/WHEEL
tstringlogger-1.0.0.dist-info/RECORD
