Metadata-Version: 2.4
Name: tstringlogger
Version: 1.0.0
Summary: Add support for using t-strings for logging
Project-URL: repository, https://github.com/pR0Ps/tstringlogger.git
License-Expression: LGPL-3.0-only
Classifier: Development Status :: 3 - Alpha
Classifier: Intended Audience :: Developers
Classifier: Programming Language :: Python :: 3.14
Classifier: Programming Language :: Python :: 3.15
Requires-Python: >=3.14
